nile_coverage/__init__.py
nile_coverage/commands.py
nile_coverage/common.py
nile_coverage/plugins.py
nile_coverage/utils.py
nile_coverage/vendor/cairo_coverage.py
nile_coverage/vendor/reporters.py
nile_coverage/xdist/remote.py
nile_coverage/xdist/worker.py
nile_coverage-0.2.5.1.dist-info/LICENSE.txt
nile_coverage-0.2.5.1.dist-info/METADATA
nile_coverage-0.2.5.1.dist-info/WHEEL
nile_coverage-0.2.5.1.dist-info/entry_points.txt
nile_coverage-0.2.5.1.dist-info/top_level.txt
nile_coverage-0.2.5.1.dist-info/RECORD
