Metadata-Version: 2.1
Name: nile-coverage
Version: 0.2.5.1
Summary: Nile plugin adding coverage reports for Cairo Smart Contracts.
Home-page: https://github.com/ericnordelo/nile-coverage
Author: "Eric Nordelo"
Author-email: "eric.nordelo39@gmail.com"
License: "MIT"
Platform: any
Classifier: Development Status :: 4 - Beta
Classifier: Programming Language :: Python
Requires-Python: >=3.8
License-File: LICENSE.txt
Requires-Dist: cairo-nile (>=0.11.0)
Requires-Dist: pytest-xdist (>=3.0.2)
Requires-Dist: asynctest (>=0.13.0)
Requires-Dist: pycobertura (>=3.0.0)
Provides-Extra: testing
Requires-Dist: setuptools ; extra == 'testing'
Requires-Dist: pytest ; extra == 'testing'
